{
	"url": "https://sample.zendesk.com/api/v2/dynamic_content/items/114093979973.json",
	"id": 114093979973,
	"name": "Access to the e-mail",
	"placeholder": "{{dc.access_to_the_e-mail}}",
	"default_locale_id": 27,
	"outdated": false,
	"created_at": "2017-09-07T06:56:19Z",
	"updated_at": "2017-09-26T14:33:19Z",
	"variants": [{
		"url": "https://sample.zendesk.com/api/v2/dynamic_content/items/114093979973/variants/114094024253.json",
		"id": 114094024253,
		"content": "Есть ли доступ к почте, к которой привязан аккаунт?",
		"locale_id": 27,
		"outdated": false,
		"active": true,
		"default": true,
		"created_at": "2017-09-07T06:56:19Z",
		"updated_at": "2017-09-26T14:33:19Z"
	}]
}
